googlesheets_to_scatterplot/__init__.py
googlesheets_to_scatterplot-0.0.12.dist-info/LICENSE.txt
googlesheets_to_scatterplot-0.0.12.dist-info/METADATA
googlesheets_to_scatterplot-0.0.12.dist-info/WHEEL
googlesheets_to_scatterplot-0.0.12.dist-info/top_level.txt
googlesheets_to_scatterplot-0.0.12.dist-info/RECORD
